setup.cfg
setup.py
bin/us-shapes.py
usshapes/__init__.py
usshapes/converter.py
usshapes/formatter.py
usshapes/indexer.py
usshapes/loader.py
usshapes/mapper.py
usshapes/utils.py
usshapes.egg-info/PKG-INFO
usshapes.egg-info/SOURCES.txt
usshapes.egg-info/dependency_links.txt
usshapes.egg-info/requires.txt
usshapes.egg-info/top_level.txt