Metadata-Version: 1.0
Name: usshapes
Version: 0.6.0
Summary: Create an Elasticsearch index of United States shapefiles, and generate a suggestions index for those locations
Home-page: https://github.com/fatisar/us-shapes
Author: Daniel Sarfati
Author-email: daniel@knockrentals.com
License: UNKNOWN
Platform: UNKNOWN
